// class version 61.0 (61)
// access flags 0x21
public class src/Main_classTest {

  // compiled from: Main_classTest.java

  // access flags 0x1
  public <init>()V
   L0
    LINENUMBER 7 L0
    ALOAD 0
    INVOKESPECIAL java/lang/Object.<init> ()V
    RETURN
   L1
    LOCALVARIABLE this Lsrc/Main_classTest; L0 L1 0
    MAXSTACK = 1
    MAXLOCALS = 1

  // access flags 0x1
  public testMonthly_rate()V
  @Lorg/junit/Test;()
   L0
    LINENUMBER 15 L0
    NEW src/Main_class
    DUP
    INVOKESPECIAL src/Main_class.<init> ()V
    ASTORE 1
   L1
    LINENUMBER 16 L1
    DCONST_0
    ALOAD 1
    POP
    DCONST_0
    DCONST_0
    INVOKESTATIC src/Main_class.monthly_rate (DD)D
    INVOKESTATIC org/junit/jupiter/api/Assertions.assertEquals (DD)V
   L2
    LINENUMBER 17 L2
    DCONST_0
    ALOAD 1
    POP
    LDC -2.0
    LDC -100.0
    INVOKESTATIC src/Main_class.monthly_rate (DD)D
    POP2
    POP2
   L3
    LINENUMBER 18 L3
    LDC 50.0
    ALOAD 1
    POP
    LDC 5000.0
    LDC 12.0
    INVOKESTATIC src/Main_class.monthly_rate (DD)D
    INVOKESTATIC org/junit/jupiter/api/Assertions.assertEquals (DD)V
   L4
    LINENUMBER 19 L4
    RETURN
   L5
    LOCALVARIABLE this Lsrc/Main_classTest; L0 L5 0
    LOCALVARIABLE mc Lsrc/Main_class; L1 L5 1
    MAXSTACK = 6
    MAXLOCALS = 2

  // access flags 0x1
  public testAmount_()V
  @Lorg/junit/Test;()
   L0
    LINENUMBER 35 L0
    NEW src/Main_class
    DUP
    INVOKESPECIAL src/Main_class.<init> ()V
    ASTORE 1
   L1
    LINENUMBER 36 L1
    DCONST_0
    ALOAD 1
    POP
    LDC -1.0
    LDC -1.0
    ICONST_M1
    INVOKESTATIC src/Main_class.amount_ (DDI)D
    INVOKESTATIC org/junit/jupiter/api/Assertions.assertEquals (DD)V
   L2
    LINENUMBER 37 L2
    DCONST_0
    ALOAD 1
    POP
    DCONST_0
    DCONST_0
    ICONST_0
    INVOKESTATIC src/Main_class.amount_ (DDI)D
    INVOKESTATIC org/junit/jupiter/api/Assertions.assertEquals (DD)V
   L3
    LINENUMBER 38 L3
    LDC 5300.0
    ALOAD 1
    POP
    LDC 5000.0
    LDC 12.0
    BIPUSH 6
    INVOKESTATIC src/Main_class.amount_ (DDI)D
    INVOKESTATIC org/junit/jupiter/api/Assertions.assertEquals (DD)V
   L4
    LINENUMBER 39 L4
    RETURN
   L5
    LOCALVARIABLE this Lsrc/Main_classTest; L0 L5 0
    LOCALVARIABLE mc Lsrc/Main_class; L1 L5 1
    MAXSTACK = 7
    MAXLOCALS = 2
}

   LINENUMBER 27 L0
    NEW src/Main_class
    DUP
    INVOKESPECIAL src/Main_class.<init> ()V
    ASTORE 1
   L1
    LINENUMBER 28 L1
    DCONST_0
    ALOAD 1
    POP
    LDC -1.0
    LDC -1.0
    ICONST_M1
    INVOKESTATIC src/Main_class.amount_ (DDI)D
    INVOKESTATIC org/junit/jupiter/api/Assertions.assertEquals (DD)V
   L2
    LINENUMBER 29 L2
    DCONST_0
    ALOAD 1
    POP
    DCONST_0
    DCONST_0
    ICONST_0
    INVOKESTATIC src/Main_class.amount_ (DDI)D
    INVOKESTATIC org/junit/jupiter/api/Assertions.assertEquals (DD)V
   L3
    LINENUMBER 30 L3
    LDC 5300.0
    ALOAD 1
    POP
    LDC 5000.0
    LDC 12.0
    BIPUSH 6
    INVOKESTATIC src/Main_class.amount_ (DDI)D
    INVOKESTATIC org/junit/jupiter/api/Assertions.assertEquals (DD)V
   L4
    LINENUMBER 31 L4
    RETURN
   L5
    LOCALVARIABLE this Lsrc/Main_classTest; L0 L5 0
    LOCALVARIABLE mc Lsrc/Main_class; L1 L5 1
    MAXSTACK = 7
    MAXLOCALS = 2
}

