// class version 61.0 (61)
// access flags 0x21
public class src/Main_class {

  // compiled from: Main_class.java
  // access flags 0x19
  public final static INNERCLASS java/lang/invoke/MethodHandles$Lookup java/lang/invoke/MethodHandles Lookup

  // access flags 0x1
  public <init>()V
   L0
    LINENUMBER 5 L0
    ALOAD 0
    INVOKESPECIAL java/lang/Object.<init> ()V
    RETURN
   L1
    LOCALVARIABLE this Lsrc/Main_class; L0 L1 0
    MAXSTACK = 1
    MAXLOCALS = 1

  // access flags 0x8
  static monthly_rate(DD)D
   L0
    LINENUMBER 14 L0
    DCONST_0
    DSTORE 4
   L1
    LINENUMBER 15 L1
    DLOAD 0
    DLOAD 2
    LDC 12.0
    DDIV
    DMUL
    LDC 0.01
    DMUL
    DSTORE 4
   L2
    LINENUMBER 16 L2
    DLOAD 0
    DCONST_0
    DCMPG
    IFLT L3
    DLOAD 2
    DCONST_0
    DCMPG
    IFGE L4
   L3
    LINENUMBER 18 L3
   FRAME FULL [D D D] []
    DCONST_0
    DSTORE 4
   L4
    LINENUMBER 20 L4
   FRAME FULL [D D D] []
    DLOAD 4
    DRETURN
   L5
    LOCALVARIABLE debt D L0 L5 0
    LOCALVARIABLE IR D L0 L5 2
    LOCALVARIABLE monthly_rate D L1 L5 4
    MAXSTACK = 6
    MAXLOCALS = 6

  // access flags 0x8
  static amount_(DDI)D
   L0
    LINENUMBER 39 L0
    DLOAD 0
    DLOAD 0
    DLOAD 2
    LDC 12.0
    DDIV
    DMUL
    ILOAD 4
    I2D
    DMUL
    LDC 100.0
    DMUL
    DADD
    DSTORE 5
   L1
    LINENUMBER 40 L1
    DLOAD 5
    DCONST_0
    DCMPG
    IFGE L2
   L3
    LINENUMBER 42 L3
    DCONST_0
    DRETURN
   L2
    LINENUMBER 45 L2
   FRAME FULL [D D I D] []
    DLOAD 5
    DRETURN
   L4
    LOCALVARIABLE debt D L0 L4 0
    LOCALVARIABLE IR D L0 L4 2
    LOCALVARIABLE months I L0 L4 4
    LOCALVARIABLE amount D L1 L4 5
    MAXSTACK = 8
    MAXLOCALS = 7

  // access flags 0x9
  public static main([Ljava/lang/String;)V
   L0
    LINENUMBER 54 L0
    NEW java/util/Scanner
    DUP
    GETSTATIC java/lang/System.in : Ljava/io/InputStream;
    INVOKESPECIAL java/util/Scanner.<init> (Ljava/io/InputStream;)V
    ASTORE 1
   L1
    LINENUMBER 55 L1
    GETSTATIC java/lang/System.out : Ljava/io/PrintStream;
    LDC "Enter Debt Value"
    INVOKEVIRTUAL java/io/PrintStream.println (Ljava/lang/String;)V
   L2
    LINENUMBER 56 L2
    ALOAD 1
    INVOKEVIRTUAL java/util/Scanner.nextDouble ()D
    DSTORE 2
   L3
    LINENUMBER 57 L3
    GETSTATIC java/lang/System.out : Ljava/io/PrintStream;
    LDC "Enter Interest Rate"
    INVOKEVIRTUAL java/io/PrintStream.println (Ljava/lang/String;)V
   L4
    LINENUMBER 58 L4
    ALOAD 1
    INVOKEVIRTUAL java/util/Scanner.nextDouble ()D
    DSTORE 4
   L5
    LINENUMBER 59 L5
    GETSTATIC java/lang/System.out : Ljava/io/PrintStream;
    LDC "Enter Duration in months"
    INVOKEVIRTUAL java/io/PrintStream.println (Ljava/lang/String;)V
   L6
    LINENUMBER 60 L6
    ALOAD 1
    INVOKEVIRTUAL java/util/Scanner.nextInt ()I
    ISTORE 6
   L7
    LINENUMBER 61 L7
    GETSTATIC java/lang/System.out : Ljava/io/PrintStream;
    DLOAD 2
    DLOAD 4
    ILOAD 6
    INVOKEDYNAMIC makeConcatWithConstants(DDI)Ljava/lang/String; [
      // handle kind 0x6 : INVOKESTATIC
      java/lang/invoke/StringConcatFactory.makeConcatWithConstants(Ljava/lang/invoke/MethodHandles$Lookup;Ljava/lang/String;Ljava/lang/invoke/MethodType;Ljava/lang/String;[Ljava/lang/Object;)Ljava/lang/invoke/CallSite;
      // arguments:
      "1. Debt: \u0001 Euros\n2. Interest rate: \u0001% \n3. Duration: \u0001 Months"
    ]
    INVOKEVIRTUAL java/io/PrintStream.println (Ljava/lang/String;)V
   L8
    LINENUMBER 62 L8
    DCONST_0
    DSTORE 7
   L9
    LINENUMBER 63 L9
    ALOAD 1
    INVOKEVIRTUAL java/util/Scanner.close ()V
   L10
    LINENUMBER 64 L10
    DLOAD 2
    DLOAD 4
    INVOKESTATIC src/Main_class.monthly_rate (DD)D
    DSTORE 7
   L11
    LINENUMBER 65 L11
    GETSTATIC java/lang/System.out : Ljava/io/PrintStream;
    DLOAD 7
    INVOKEDYNAMIC makeConcatWithConstants(D)Ljava/lang/String; [
      // handle kind 0x6 : INVOKESTATIC
      java/lang/invoke/StringConcatFactory.makeConcatWithConstants(Ljava/lang/invoke/MethodHandles$Lookup;Ljava/lang/String;Ljava/lang/invoke/MethodType;Ljava/lang/String;[Ljava/lang/Object;)Ljava/lang/invoke/CallSite;
      // arguments:
      "4. Monthly amount is \u0001 Euros"
    ]
    INVOKEVIRTUAL java/io/PrintStream.println (Ljava/lang/String;)V
   L12
    LINENUMBER 66 L12
    GETSTATIC java/lang/System.out : Ljava/io/PrintStream;
    ILOAD 6
    INVOKEDYNAMIC makeConcatWithConstants(I)Ljava/lang/String; [
      // handle kind 0x6 : INVOKESTATIC
      java/lang/invoke/StringConcatFactory.makeConcatWithConstants(Ljava/lang/invoke/MethodHandles$Lookup;Ljava/lang/String;Ljava/lang/invoke/MethodType;Ljava/lang/String;[Ljava/lang/Object;)Ljava/lang/invoke/CallSite;
      // arguments:
      "5. Number of rates are \u0001"
    ]
    INVOKEVIRTUAL java/io/PrintStream.println (Ljava/lang/String;)V
   L13
    LINENUMBER 67 L13
    GETSTATIC java/lang/System.out : Ljava/io/PrintStream;
    DLOAD 2
    DLOAD 4
    ILOAD 6
    INVOKESTATIC src/Main_class.amount_ (DDI)D
    INVOKEDYNAMIC makeConcatWithConstants(D)Ljava/lang/String; [
      // handle kind 0x6 : INVOKESTATIC
      java/lang/invoke/StringConcatFactory.makeConcatWithConstants(Ljava/lang/invoke/MethodHandles$Lookup;Ljava/lang/String;Ljava/lang/invoke/MethodType;Ljava/lang/String;[Ljava/lang/Object;)Ljava/lang/invoke/CallSite;
      // arguments:
      "6. Over all amount with interest is \u0001 Euros"
    ]
    INVOKEVIRTUAL java/io/PrintStream.println (Ljava/lang/String;)V
   L14
    LINENUMBER 71 L14
    RETURN
   L15
    LOCALVARIABLE args [Ljava/lang/String; L0 L15 0
    LOCALVARIABLE myObj Ljava/util/Scanner; L1 L15 1
    LOCALVARIABLE debt D L3 L15 2
    LOCALVARIABLE interest D L5 L15 4
    LOCALVARIABLE duration I L7 L15 6
    LOCALVARIABLE m_rate D L9 L15 7
    MAXSTACK = 6
    MAXLOCALS = 9
}

va/lang/String; L0 L14 0
    LOCALVARIABLE myObj Ljava/util/Scanner; L1 L14 1
    LOCALVARIABLE debt D L3 L14 2
    LOCALVARIABLE interest D L5 L14 4
    LOCALVARIABLE duration I L7 L14 6
    LOCALVARIABLE m_rate D L9 L14 7
    MAXSTACK = 6
    MAXLOCALS = 9
}

